MANIFEST.in
README.md
setup.cfg
setup.py
seqenv/__init__.py
seqenv/analysis.py
seqenv/ontology.py
seqenv/outputs.py
seqenv/seqenv
seqenv.egg-info/PKG-INFO
seqenv.egg-info/SOURCES.txt
seqenv.egg-info/dependency_links.txt
seqenv.egg-info/requires.txt
seqenv.egg-info/top_level.txt
seqenv/common/__init__.py
seqenv/common/autopaths.py
seqenv/common/cache.py
seqenv/common/color.py
seqenv/common/database.py
seqenv/common/git.py
seqenv/common/timer.py
seqenv/common/tmpstuff.py
seqenv/data_envo/envo.obo
seqenv/data_envo/envo_entities.tsv
seqenv/data_envo/envo_global.tsv
seqenv/data_envo/envo_groups.tsv
seqenv/data_envo/envo_names.tsv
seqenv/data_envo/envo_preferred.tsv
seqenv/data_sources/generate.py
seqenv/fasta/__init__.py
seqenv/fasta/splitable.py
seqenv/seqsearch/__init__.py
seqenv/seqsearch/blast.py
seqenv/seqsearch/parallel.py
seqenv/seqsearch/vsearch.py