Metadata-Version: 1.1
Name: seqenv
Version: 1.3.0
Summary: Assign environment ontology (EnvO) terms to DNA sequences
Home-page: https://github.com/xapple/seqenv
Author: Lucas Sinclair
Author-email: lucas.sinclair@me.com
License: MIT
Download-URL: https://github.com/xapple/seqenv/tarball/1.2.9
Platform: UNKNOWN
Classifier: Topic :: Scientific/Engineering :: Bio-Informatics
